model_log/.DS_Store
model_log/__init__.py
model_log/init_db.sql
model_log/metric_list1.pkl
model_log/metric_list2.pkl
model_log/model_log.db
model_log/modellog.py
model_log/modellog_web.py
model_log/tf_param.pkl
model_log/__pycache__/__init__.cpython-37.pyc
model_log/__pycache__/modellog.cpython-37.pyc
model_log/__pycache__/modellog_web.cpython-37.pyc
model_log/static/css/admin.css
model_log/static/css/amazeui.min.css
model_log/static/css/app.css
model_log/static/fonts/FontAwesome.otf
model_log/static/fonts/fontawesome-webfont.eot
model_log/static/fonts/fontawesome-webfont.ttf
model_log/static/fonts/fontawesome-webfont.woff
model_log/static/fonts/fontawesome-webfont.woff2
model_log/static/i/app-icon72x72@2x.png
model_log/static/i/favicon.png
model_log/static/i/startup-640x1096.png
model_log/static/i/examples/admin-chrome.png
model_log/static/i/examples/admin-firefox.png
model_log/static/i/examples/admin-ie.png
model_log/static/i/examples/admin-opera.png
model_log/static/i/examples/admin-safari.png
model_log/static/i/examples/adminPage.png
model_log/static/i/examples/blogPage.png
model_log/static/i/examples/landing.png
model_log/static/i/examples/landingPage.png
model_log/static/i/examples/loginPage.png
model_log/static/i/examples/sidebarPage.png
model_log/static/img/logo.png
model_log/static/js/amazeui.min.js
model_log/static/js/app.js
model_log/static/js/echarts.min.js
model_log/static/js/iscroll.js
model_log/static/js/jquery.min.js
model_log/templates/__init__.py
model_log/templates/alert.html
model_log/templates/index.html
model_log/templates/model_detail.html
model_log/templates/__pycache__/__init__.cpython-38.pyc
model_log-1.1.9.dist-info/METADATA
model_log-1.1.9.dist-info/WHEEL
model_log-1.1.9.dist-info/entry_points.txt
model_log-1.1.9.dist-info/top_level.txt
model_log-1.1.9.dist-info/zip-safe
model_log-1.1.9.dist-info/RECORD
