Metadata-Version: 2.1
Name: model-log
Version: 1.1.9
Summary: test description
Home-page: https://github.com/NLP-LOVE
Author: mantch
Author-email: mantchs@163.com
License: MIT
Keywords: python ML DL model log
Platform: UNKNOWN
Requires-Dist: flask (>=0.11)
